hotviz/__init__.py
hotviz/hot_text.py
hotviz/hot_tree.py
hotviz/example/__init__.py
hotviz/example/span_data.py
hotviz/example/tree_data.py
hotviz-0.0.9.dist-info/LICENSE
hotviz-0.0.9.dist-info/METADATA
hotviz-0.0.9.dist-info/WHEEL
hotviz-0.0.9.dist-info/top_level.txt
hotviz-0.0.9.dist-info/RECORD
